dirclass/__init__.py
dirclass/core.py
dirclass-0.1.0.dist-info/licenses/LICENSE
dirclass-0.1.0.dist-info/METADATA
dirclass-0.1.0.dist-info/WHEEL
dirclass-0.1.0.dist-info/top_level.txt
dirclass-0.1.0.dist-info/RECORD
