Metadata-Version: 2.4
Name: dirclass
Version: 0.1.0
Summary: Treat a directory like a dataclass for recursive file listing and reading.
Author-email: Rongxin Ouyang <rongxin@u.nus.edu>
License-Expression: MIT
Keywords: files,directories,dataclass,recursion,utilities
Classifier: Programming Language :: Python :: 3
Classifier: Programming Language :: Python :: 3 :: Only
Classifier: Programming Language :: Python :: 3.10
Classifier: Operating System :: OS Independent
Requires-Python: >=3.10
License-File: LICENSE
Dynamic: license-file
